[
    {
        "date": "Tue, Aug 30",
        "title": "Lecture 1: Introduction",
        "materials": [
            {
                "title": "Lecture Slides",
                "url": "https://docs.google.com/presentation/d/1x2HXPMA6TDQbtExL_gDgxyyUlcyrd4zTwNv64OcDZss/edit?usp=sharing"
                },
                {
                "title": "Lecture Notebook",
                "url": "https://datahub.berkeley.edu/hub/user-redirect/git-pull?repo=https%3A%2F%2Fgithub.com%2Fdata-88e%2Ffa22-student&branch=main&urlpath=retro%2Ftree%2Ffa22-student%2Flec%2Flec01%2Flec01.ipynb"
                }
        ],
        "assignment": [
        ]
    },
    {
        "date": "Tue, Sep 6",
        "title": "Lecture 2: Demand",
        "materials": [
            {
                "title": "Building a Demand Curve",
                "url": "https://datahub.berkeley.edu/hub/user-redirect/git-pull?repo=https%3A%2F%2Fgithub.com%2Fdata-88e%2Ffa22-student&branch=main&urlpath=tree%2Ffa22-student%2Flec%2Flec02%2Fdemand-curve.ipynb"
            },
            {
                "title": "Lecture 2 - Part 2 RISE Notebook",
                "url": "https://datahub.berkeley.edu/hub/user-redirect/git-pull?repo=https%3A%2F%2Fgithub.com%2Fdata-88e%2Ffa22-student&branch=main&urlpath=tree%2Ffa22-student%2Flec%2Flec02%2Fslides-pt2.ipynb"
            }
        ],
        "assignment": [
            {
                "title": "Lab 1",
                "dueDate": "Sep 12",
                "url": "https://datahub.berkeley.edu/hub/user-redirect/git-pull?repo=https%3A%2F%2Fgithub.com%2Fdata-88e%2Ffa22-student&branch=main&urlpath=tree%2Ffa22-student%2Flab%2Flab01%2Flab01.ipynb"
            },
            {
                "title": "Project 1",
                "dueDate": "Sep 26",
                "url": "https://datahub.berkeley.edu/hub/user-redirect/git-pull?repo=https%3A%2F%2Fgithub.com%2Fdata-88e%2Ffa22-student&branch=main&urlpath=tree%2Ffa22-student%2Fproj%2Fproj01%2Fproj01.ipynb"
            }
        ]
    },
    {
        "date": "Tue, Sep 13",
        "title": "Lecture 3: Supply",
        "materials": [
        ],
        "assignment": [
        ]
    },
    {
        "date": "Tue, Sep 20",
        "title": "Lecture 4: Government Intervention",
        "materials": [
        ],
        "assignment": [
        ]
    },
    {
        "date": "Tue, Sep 27",
        "title": "Lecture 5: Production",
        "materials": [
        ],
        "assignment": [
        ]
    },
    {
        "date": "Tue, Oct 4",
        "title": "Lecture 6: Utility",
        "materials": [
        ],
        "assignment": [
        ]
    },
    {
        "date": "Tue, Oct 11",
        "title": "Lecture 7: Inequality",
        "materials": [
        ],
        "assignment": [
        ]
    },
    {
        "date": "Tue, Oct 18",
        "title": "Lecture 8: Game Theory",
        "materials": [
        ],
        "assignment": [
        ]
    },
    {
        "date": "Tue, Oct 25",
        "title": "Lecture 9: Development",
        "materials": [
        ],
        "assignment": [
        ]
    },
    {
        "date": "Tue, Nov 1",
        "title": "Lecture 10: Macroeconomic Policy",
        "materials": [
        ],
        "assignment": [
        ]
    },
    {
        "date": "Tue, Nov 8",
        "title": "Lecture 11: Finance",
        "materials": [
        ],
        "assignment": [
        ]
    },
    {
        "date": "Tue, Nov 15",
        "title": "Lecture 12: Econometrics",
        "materials": [
        ],
        "assignment": [
        ]
    },
    {
        "date": "Tue, Nov 22",
        "title": "Lecture 13: Environmental Economics",
        "materials": [
        ],
        "assignment": [
        ]
    },
    {
        "date": "Tue, Nov 29",
        "title": "Lecture 14: Guest Lecture",
        "materials": [
        ],
        "assignment": [
        ]
    }
]
